{
  "file_id": "file_d47c1fd8646e",
  "source_path": "C:\\IntelliCV\\data\\Emily Nuber.pdf",
  "extracted_at": "2025-08-10T16:25:26.754533",
  "text": " \n  \nCandidate :  Emily Nuber  \n \n \nPERSONAL DETAILS  \n  \nLocation:   Germany - Norderstedt  \n \n \nQUALIFICATIONS  \n \nMicro - and Macro -, Supply -Side- and Mathematical Economics  - Oct 2004 – May 2011 University of \nHamburg  \n \nProfession al Educ ation  \nJun 2019 Multipliers Training Business Results Group, London  \nJul 2018  Advancing Negotiations Skills Scotwork, Stuttgart  \nMay 2 017 Coaching Practices for Leaders Lee Hecht Harrison, Hamburg  \nMarch – May 2016 LOPD Führungskräftetraining LUCAS Consulting, Hamburg  \nAug 2013 Erstmals Vorgesetzter Haufe Akademie, Hamburg  \nAug 2013 Erfolgreiches Projektmanagement (Modul I) (Die Aka demie für Führungskräfte, \nVisselhövede)  \nFeb 2013  Base Oils – an in -depth introduction & the next level: product quality economics and \nprofitability ICIS  \n  \nCandidate :  Emily Nuber  \n \n \nPERSONAL DETAILS  \n  \nLocation:   Germany - Norderstedt  \n \n \nQUALIFICATIONS  \n \nMicro - and Macro -, Supply -Side- and Mathematical Economics  - Oct 2004 – May 2011 University of \nHamburg  \n \nProfession al Educ ation  \nJun 2019 Multipliers Training Business Results Group, London  \nJul 2018  Advancing Negotiations Skills Scotwork, Stuttgart  \nMay 2 017 Coaching Practices for Leaders Lee Hecht Harrison, Hamburg  \nMarch – May 2016 LOPD Führungskräftetraining LUCAS Consulting, Hamburg  \nAug 2013 Erstmals Vorgesetzter Haufe Akademie, Hamburg  \nAug 2013 Erfolgreiches Projektmanagement (Modul I) (Die Aka demie für Führungskräfte, \nVisselhövede)  \nFeb 2013  Base Oils – an in -depth introduction & the next level: product quality economics and \nprofitability ICIS, London  \nNov 2012  Überzeugende Verhandlungsführung Die Akademie für Führungskräfte, Hamburg  \n \nLanguages  \nGerman (Native)  \nEnglish (Fluent)  \nSpanish  (Beginner ) \n \n \nCARE ER SUMMARY  \n \n2011 – date Hywax GmbH (formerly Sasol Wax GmbH)  \n \nMarch 2022 – present Hywax GmbH  \nPosition: Manager Strategic Sourcing Wax  \n• Prokurist  \n \nJan 2015 – present  Sasol Wax GmbH  \nPosition: Manager Strategic Sourcing Wax & Phenolics Sasol  \n• Management of the department Strategic Sourcing Wax & Phenolics for strategic raw materials, \nwith five direct reports and a sourcing budget of approx. EUR 300m p.a.  \n• Leadership of and intense contribution to international crossfunctional Strategic Sourcing \nprojects  \n • Define, develop, negotiate and implement mid to long -term supply strategies for strategic raw \nmaterials to ensure suffic ient feedstock supply and competitiveness in the marketplace  \n• Establish and maintain key business relationships with suppliers  \n• Continuous company economics results improvement through responsible buying for complex, \nstrategic and cross -site commodity gr oups considering logistics constraints  \n• Continuous monitoring and analysis of international procurement markets and market trends  \n \nJan 2014 - Dec 2014  \nPosit ion: Deputy Head of Raw Material Procurement  \n• Involvement in mid to long -term raw material  supply strategies  \n• Lead commercial support team  \n• Price and quality conscious sourcing of raw materials taking into account relevant logistics and \nquality factors, as well as risk assessment on the basis of valid sourcing procedures and \nguidelines  \n \nAug 2011 - Dec 2013  \nPosition:  Buyer Raw Materials  \n• Analysis of development of raw material quotations  \n• Development and proposals of price formulas to existing and new suppliers  \n• Focal point to Sales & Marketing in terms of price trends and raw materi al availability  \n• Sourcing of Fisher Tropsch Waxes  \n• Securing supply of raw materials for the satellite production plants  \n• Developing, implementation and execution of base oil strategies and giving support from the \nanalytical point of view  \n \nJan 2010 – July 2011 Airbus Operations GmbH  \nPosition:  Working Student – Investment Procurement in the Commodity Land & Buildings  \n• Preparation and realization of contract negotiations  \n• Preparation of strategic tender selection reports  \n• Independent conduction of operational purchasing tasks fo r multi -million Airbus/ EADS Building \nprojects.  \n• Support of strategic building investment projects  \n• Co-lead of multi -functional - teams  \n \nJul 2007 – Oct 2009 Kelly Services GmbH & Co. KG  \nPosition:  Working Student – Human Resources  \n• Providing support to the HR re cruitment consultants  \n \n COMMENT  \n \nExper ience  \nLead ership  \nTurnaround management  \nCrossfunctional teamwork  \nRaw Material Procurement  \nInvestment/ Technical Procurement  \nContract Management  \nInbound Logistics (Vessel chartering, Tank trucks, Isotainer, Railtank Cars)  \n \nSkills  \n• Complex negotiations  \n• Analyti cal thinking  \n• Perfomance driven  \n \nComputer  Skills \n• Microsoft Office  \n• SAP R3  \n• IBM AS/400  \n• Ariba (Bidding Tool)  \n \nFor further information please contact Julie Smith  on 01695 5 70 696 or email julie.smith @johnston -\nvere.co.uk  \n \n \n ",
  "emails": [],
  "phones": [],
  "names": [
    "Advancing Negotiations",
    "Skills Scotwork",
    "Working Student"
  ],
  "work_history": [],
  "title": "",
  "company": "",
  "location": "",
  "experience_years": 0,
  "career_stage": "entry",
  "industries": [
    "general"
  ],
  "skills": [
    "leadership"
  ],
  "ai_scores": {
    "experience_years": 0.0,
    "title_progression": 0.5,
    "company_prestige": 0.5,
    "location_mobility": 0.5,
    "skill_diversity": 0.1,
    "network_strength": 0.3
  },
  "ai_final_score": 0.285,
  "ai_processed_at": "2025-08-11T10:42:13.818514",
  "similar_users": [
    {
      "user_id": "file_002a746786ae",
      "similarity_score": 1.0,
      "career_stage": "entry",
      "industries": [
        "general"
      ],
      "ai_score": 0.285,
      "experience_years": 0
    },
    {
      "user_id": "file_00712ee6c7f2",
      "similarity_score": 1.0,
      "career_stage": "entry",
      "industries": [
        "general"
      ],
      "ai_score": 0.285,
      "experience_years": 0
    },
    {
      "user_id": "file_027109a8b87b",
      "similarity_score": 1.0,
      "career_stage": "entry",
      "industries": [
        "general"
      ],
      "ai_score": 0.285,
      "experience_years": 0
    },
    {
      "user_id": "file_02f7e7d2c8b1",
      "similarity_score": 1.0,
      "career_stage": "entry",
      "industries": [
        "general"
      ],
      "ai_score": 0.285,
      "experience_years": 0
    },
    {
      "user_id": "file_04294f989b58",
      "similarity_score": 1.0,
      "career_stage": "entry",
      "industries": [
        "general"
      ],
      "ai_score": 0.285,
      "experience_years": 0
    },
    {
      "user_id": "file_04616388d705",
      "similarity_score": 1.0,
      "career_stage": "entry",
      "industries": [
        "general"
      ],
      "ai_score": 0.285,
      "experience_years": 0
    },
    {
      "user_id": "file_04ea4eda87b4",
      "similarity_score": 1.0,
      "career_stage": "entry",
      "industries": [
        "general"
      ],
      "ai_score": 0.285,
      "experience_years": 0
    },
    {
      "user_id": "file_05d5423305d7",
      "similarity_score": 1.0,
      "career_stage": "entry",
      "industries": [
        "general"
      ],
      "ai_score": 0.285,
      "experience_years": 0
    },
    {
      "user_id": "file_065fd472fa7a",
      "similarity_score": 1.0,
      "career_stage": "entry",
      "industries": [
        "general"
      ],
      "ai_score": 0.285,
      "experience_years": 0
    },
    {
      "user_id": "file_06ae3a824a08",
      "similarity_score": 1.0,
      "career_stage": "entry",
      "industries": [
        "general"
      ],
      "ai_score": 0.285,
      "experience_years": 0
    }
  ],
  "recommendations": {
    "career_advancement": [
      "Focus on building core technical skills",
      "Seek mentorship from senior team members",
      "Take on challenging projects to gain experience"
    ],
    "skill_development": [],
    "company_targets": [
      "Mid-size companies with growth potential",
      "Startups in emerging industries",
      "Companies known for employee development"
    ],
    "networking": []
  }
}