{
  "file_id": "file_8153989030b0",
  "source_path": "C:\\IntelliCV\\data\\doc_data_converted_docx\\Fizza Sabir.docx",
  "extracted_at": "2025-08-10T16:26:32.800941",
  "text": "CANDIDATE \t\tFizza Sabir\nPERSONAL DETAILS\nLocation:\t\tUnited Arab Emirates – Dubai\nQUALIFICATIONS\nINSEAD, Leading Digital Transformation 2019\nCIPD, Level 5 Certification 2018\nCertified Human Resources management, CHRM 2012\nMBA in International Business - University of East London, London, UK. 2007\nMBA Foundation Programme - School of Technology and Management, London, UK.2006\nBA (Hons) in Media and Journalism - The Social and Political University, Baku, Azerbaijan.2005\nTraining:\nCutting Edge (cut-e) Psychometric assessor\nMindful Leadership o First Aid Trainer Certificate\nHSE in DNV GL - Incident reporting and Travel Safety\nDNV GL Leadership Expectations\nDealing with Dilemmas\nBasic Health, Safety and Environment\nDNV GL Compensation\nSurvival guide for new managers\nManaging Individual Performan CANDIDATE \t\tFizza Sabir\nPERSONAL DETAILS\nLocation:\t\tUnited Arab Emirates – Dubai\nQUALIFICATIONS\nINSEAD, Leading Digital Transformation 2019\nCIPD, Level 5 Certification 2018\nCertified Human Resources management, CHRM 2012\nMBA in International Business - University of East London, London, UK. 2007\nMBA Foundation Programme - School of Technology and Management, London, UK.2006\nBA (Hons) in Media and Journalism - The Social and Political University, Baku, Azerbaijan.2005\nTraining:\nCutting Edge (cut-e) Psychometric assessor\nMindful Leadership o First Aid Trainer Certificate\nHSE in DNV GL - Incident reporting and Travel Safety\nDNV GL Leadership Expectations\nDealing with Dilemmas\nBasic Health, Safety and Environment\nDNV GL Compensation\nSurvival guide for new managers\nManaging Individual Performance, MIP for Employees\nStepping into the Leadership\nLanguages\nEnglish, Russian, Azeri and Turkish\nCAREER SUMMARY\n2014 to date DNV\n2019 to date\nPosition: Senior Regional People Advisor and Lead of Nationalization\nPrevious roles with DNV:\nHR Manager Middle East 2014-1017\nHR Manager Middle East and Sub-Sahara 2017-2019\nBusiness Partnering and Strategic HR Advisory:\nStrategic stakeholder management and Advisory to the Business Areas –, Energy Systems, Oil&Gas, Maritime services, Business Assurance and Digital Solutions\nEngaging Senior Management by providing expert advice, coaching and support on full range of HR activities (including policies and procedures, terms and conditions of employment, restructuring of services, performance management, redundancy planning.\nEstablishes effective resourcing, mobility, development, succession and retention plans for leadership teams / key roles across, Influence talent, performance and mobility decisions\nIn consultation with the HQ the implementation and roll out of standardized services as per Service Level Agreements\nOversees cultural transformation, organization design and change management post-merger and support business in enhancement of employee engagement, implementation of diversity initiatives, and ensure culture of ethical behaviour at an individual and collective level.\nReview and implementation of HR Policies, OPs and procedures for Middle East and North Africa\nTalent Acquisition, Management of Assessment centers and Employer Branding:\nManpower planning and Strategic alignment with the BAs\nManaging talent acquisition activities and campaigns for IMEA within agreed KPIs\nDriving Graduate recruitment programs in collaboration with the top universities in the Region\nUsing various reporting tools, such as Power Bi, Glassdoor analytics, iCIMS dashboard and reporting to forecast, analyse and adopt appropriate set of actions to increase brand visibility and Diversity & Inclusion.\nSuccessful management of assessment centers in India and the ME, Cut-e certified, psychometric test administration and feedback session\nActive headhunting of the passive talent via social platforms and other networking events\nGlobal Mobility and International Assignment management:\nOverlooking international Long-term, short-term, rotation and training assignments\nMobilization and repatriation of Assignees in the region\nGrievance Management:\nConsult Line Managers and employees with disciplinary and grievance cases in line with established legislations\nManage investigations and effectively handle disciplinary and grievance matters\nFacilitate an optimum viable solution to support the business\nNationalization/Emiratisation:\nResponsible for establishing policies and procedures for attraction, retention and development of the Nationals, Employer branding activities for Nationals\nTeam Management:\nEffective team management and development of Public relations Officers (x3) and Nationals (x3) through open and transparent communication\nPerformance Management/Compensation & Benefits:\nMonitor and review performance appraisals ensuring that annual appraisals are carried out in a timely basis\nWorking closely with HayGroup and Mercer for salary benchmarking, responsible for salary review exercise and benchmarking\nCoordinating annual salary adjustment and promotion exercise, annual performance assessments\nOther activities:\nProject coordina",
  "emails": [],
  "phones": [],
  "names": [
    "Senior Recruitment",
    "United Arab",
    "Middle East"
  ],
  "work_history": [],
  "title": "",
  "company": "",
  "location": "",
  "experience_years": 0,
  "career_stage": "entry",
  "industries": [
    "general"
  ],
  "skills": [
    "analytics",
    "leadership"
  ],
  "ai_scores": {
    "experience_years": 0.0,
    "title_progression": 0.5,
    "company_prestige": 0.5,
    "location_mobility": 0.5,
    "skill_diversity": 0.2,
    "network_strength": 0.3
  },
  "ai_final_score": 0.3,
  "ai_processed_at": "2025-08-11T10:42:10.962355",
  "similar_users": [
    {
      "user_id": "file_03a6b852a8c4",
      "similarity_score": 1.0,
      "career_stage": "entry",
      "industries": [
        "general"
      ],
      "ai_score": 0.3,
      "experience_years": 0
    },
    {
      "user_id": "file_051097a5305f",
      "similarity_score": 1.0,
      "career_stage": "entry",
      "industries": [
        "general"
      ],
      "ai_score": 0.3,
      "experience_years": 0
    },
    {
      "user_id": "file_0a18a97bcfd0",
      "similarity_score": 1.0,
      "career_stage": "entry",
      "industries": [
        "general"
      ],
      "ai_score": 0.3,
      "experience_years": 0
    },
    {
      "user_id": "file_0beaec8ab0a1",
      "similarity_score": 1.0,
      "career_stage": "entry",
      "industries": [
        "general"
      ],
      "ai_score": 0.3,
      "experience_years": 0
    },
    {
      "user_id": "file_0cab440865c1",
      "similarity_score": 1.0,
      "career_stage": "entry",
      "industries": [
        "general"
      ],
      "ai_score": 0.3,
      "experience_years": 0
    },
    {
      "user_id": "file_0dfd8954822a",
      "similarity_score": 1.0,
      "career_stage": "entry",
      "industries": [
        "general"
      ],
      "ai_score": 0.3,
      "experience_years": 0
    },
    {
      "user_id": "file_0ff523b92ee7",
      "similarity_score": 1.0,
      "career_stage": "entry",
      "industries": [
        "general"
      ],
      "ai_score": 0.3,
      "experience_years": 0
    },
    {
      "user_id": "file_10d56f91128e",
      "similarity_score": 1.0,
      "career_stage": "entry",
      "industries": [
        "general"
      ],
      "ai_score": 0.3,
      "experience_years": 0
    },
    {
      "user_id": "file_12590c739be9",
      "similarity_score": 1.0,
      "career_stage": "entry",
      "industries": [
        "general"
      ],
      "ai_score": 0.3,
      "experience_years": 0
    },
    {
      "user_id": "file_12df452c4021",
      "similarity_score": 1.0,
      "career_stage": "entry",
      "industries": [
        "general"
      ],
      "ai_score": 0.3,
      "experience_years": 0
    }
  ],
  "recommendations": {
    "career_advancement": [
      "Focus on building core technical skills",
      "Seek mentorship from senior team members",
      "Take on challenging projects to gain experience"
    ],
    "skill_development": [],
    "company_targets": [
      "Mid-size companies with growth potential",
      "Startups in emerging industries",
      "Companies known for employee development"
    ],
    "networking": []
  }
}