{
  "file_id": "file_5fbebd37249c",
  "source_path": "C:\\IntelliCV\\data\\resume_versions\\uploads\\61504 Cristian Nunez Perez\\Cristian_Nunez Original Resume.pdf",
  "extracted_at": "2025-08-10T16:27:41.633361",
  "text": "CRISTIAN NÚÑEZ PÉREZMobile +34 686 17 23 40Madridcf.nunez@icloud.comwww.linkedin.com/in/cfnunez                                                                                                                                                       SUMMARY I am a selling passionate/customer oriented professional with an MBA degree and strong commercial background; I have a vast experience in sales development, managing and increasing customer portfolio and customer service.  I am a goal oriented team player, self-motivated person with a highly entrepreneur spirit who has communication and presentation skills.  I have a deep interest in business development, managing key accounts, customer interaction and the complete commercial cycle.  I am 39 years old and I have willingness for traveling.CA CRISTIAN NÚÑEZ PÉREZMobile +34 686 17 23 40Madridcf.nunez@icloud.comwww.linkedin.com/in/cfnunez                                                                                                                                                       SUMMARY I am a selling passionate/customer oriented professional with an MBA degree and strong commercial background; I have a vast experience in sales development, managing and increasing customer portfolio and customer service.  I am a goal oriented team player, self-motivated person with a highly entrepreneur spirit who has communication and presentation skills.  I have a deep interest in business development, managing key accounts, customer interaction and the complete commercial cycle.  I am 39 years old and I have willingness for traveling.CAREER HISTORY \nEDUCATION HISTORY LANGUAGES Advanced English skills in reading, writing and speakingBasic French skills in reading, writing and speaking2019-PresentSales Professional           Siemens AG.  Madrid, SpainResponsible for developing business at Medium Voltage solutions such as preventive services, corrective services and modern approaches such like digital monitoring systems.  Mainly focused on Utilities, distributed power generation companies (PV and solar), EPC’s and B2B with railways, chemicals and automation companies2018-2019Tender ConsultantIndra Sistemas.  Madrid, SpainResponsible for selling complex software solutions such as ADMS, WFM, NDM and GIS through co-authoring RFI’s & RFP’s.  Preparing and delivering presentations and software demonstrations to customers worldwide to provide technical overviews and to generate interest in new products2015-2017Key Account ManagerCVIE Electrical Facilites.  VenezuelaResponsible for planning business strategies and commercial business plans, increasing customers portfolio and building strong customer relationship with existing ones, developing B2B businesses, identifying new opportunities, set & meet proﬁt targetsAchievements Closing 25 opportunities for the company, bringing two strategic customers (a medium level bank and a hospital) to the company, building and managing ten members project teams, meeting and exceeding Customer's satisfaction goal by 99%2011-2015Customer Service Manager & Key Account ManagerAlstom-General ElectricResponsible for maximizing sales in the projects division and create new strategies to meet customer’s needs, participating actively in P&L optimization, managing CRM´s tools (SalesForce and SAP), traveling around the country to identify new business opportunities, negotiating contract agreements with customers, interact with the sales team for demand planning.Achievements to be part and close the negotiation process for a total amount of USD 14 MM service contracts, to meet and exceed 2012, 2013 and 2014 annual sales goal by 30%, to increase company´s market share by 20%.2006-2009Project EngineerEmerson Network Power.  VenezuelaResponsible for designing medium and low voltage circuits for banks and telecom Data Centers, projects quotation and supporting sales team.Achievements to accomplish the annual goal of 52 projects designed and to be part of the sales department annual goal success.2009-2010Master in Business Administration, MBA IESA Business School (Caracas, Venezuela)  4 international accreditations in academic excellence1999-2006Electrical Engineer Universidad Simón Bolívar (Caracas, Venezuela)\n ",
  "emails": [
    "40Madridcf.nunez@icloud.comwww.linkedin.com"
  ],
  "phones": [
    "+34 686 17 23"
  ],
  "names": [
    "Advanced English",
    "Key Account",
    "Medium Voltage"
  ],
  "work_history": [],
  "title": "",
  "company": "",
  "location": "",
  "experience_years": 0,
  "career_stage": "entry",
  "industries": [
    "general"
  ],
  "skills": [],
  "ai_scores": {
    "experience_years": 0.0,
    "title_progression": 0.5,
    "company_prestige": 0.5,
    "location_mobility": 0.5,
    "skill_diversity": 0.0,
    "network_strength": 0.3
  },
  "ai_final_score": 0.27,
  "ai_processed_at": "2025-08-11T10:42:09.358115",
  "similar_users": [
    {
      "user_id": "file_0003865a7c4a",
      "similarity_score": 1.0,
      "career_stage": "entry",
      "industries": [
        "general"
      ],
      "ai_score": 0.27,
      "experience_years": 0
    },
    {
      "user_id": "file_000a12cbb771",
      "similarity_score": 1.0,
      "career_stage": "entry",
      "industries": [
        "general"
      ],
      "ai_score": 0.27,
      "experience_years": 0
    },
    {
      "user_id": "file_00344b0836c2",
      "similarity_score": 1.0,
      "career_stage": "entry",
      "industries": [
        "general"
      ],
      "ai_score": 0.27,
      "experience_years": 0
    },
    {
      "user_id": "file_0086ec6f1b90",
      "similarity_score": 1.0,
      "career_stage": "entry",
      "industries": [
        "general"
      ],
      "ai_score": 0.27,
      "experience_years": 0
    },
    {
      "user_id": "file_008dcceee73c",
      "similarity_score": 1.0,
      "career_stage": "entry",
      "industries": [
        "general"
      ],
      "ai_score": 0.27,
      "experience_years": 0
    },
    {
      "user_id": "file_00e4daf72a60",
      "similarity_score": 1.0,
      "career_stage": "entry",
      "industries": [
        "general"
      ],
      "ai_score": 0.27,
      "experience_years": 0
    },
    {
      "user_id": "file_00f1ad8aa85c",
      "similarity_score": 1.0,
      "career_stage": "entry",
      "industries": [
        "general"
      ],
      "ai_score": 0.27,
      "experience_years": 0
    },
    {
      "user_id": "file_00f585667d18",
      "similarity_score": 1.0,
      "career_stage": "entry",
      "industries": [
        "general"
      ],
      "ai_score": 0.27,
      "experience_years": 0
    },
    {
      "user_id": "file_010f7e646664",
      "similarity_score": 1.0,
      "career_stage": "entry",
      "industries": [
        "general"
      ],
      "ai_score": 0.27,
      "experience_years": 0
    },
    {
      "user_id": "file_012ae853275f",
      "similarity_score": 1.0,
      "career_stage": "entry",
      "industries": [
        "general"
      ],
      "ai_score": 0.27,
      "experience_years": 0
    }
  ],
  "recommendations": {
    "career_advancement": [
      "Focus on building core technical skills",
      "Seek mentorship from senior team members",
      "Take on challenging projects to gain experience"
    ],
    "skill_development": [],
    "company_targets": [
      "Mid-size companies with growth potential",
      "Startups in emerging industries",
      "Companies known for employee development"
    ],
    "networking": []
  }
}