{
  "file_id": "file_cecfdea6cc7c",
  "source_path": "C:\\IntelliCV\\data\\resume_versions\\uploads\\61430 Sandeep Sharma\\original\\Original CV - Sandeep Sharma.pdf",
  "extracted_at": "2025-08-10T16:27:25.011689",
  "text": "   \nContact\ns.sharma4@yahoo.co.uk\nwww.linkedin.com/in/sandeep-\nsharma-0b82655  (LinkedIn)\nTop Skills\nOil\nEPC\nFEEDSandeep Sharma\nProject Director EPC at KBR (UK) LIMITED\nCamberley\nSummary\n29+ years of experience of leading and managing teams in\nCorporate and project management roles. Lead by example and\nencourage, inspire, trust and motivate teams through inclusion and\nautonomy in work execution and decision making to successfully\ndeliver on international FEED, EPC projects and growth initiatives. \nKey positions held include Director – Engineering Operations,\nProject Director - EPC, Engineering Manager, Delivery Manager, and\nEngineering & Procurement Integration Manager. \nResponsible for Profit & Loss (P&L) and budget management\non medium to large FEED and EPC projects with all types of\ncom    \nContact\ns.sharma4@yahoo.co.uk\nwww.linkedin.com/in/sandeep-\nsharma-0b82655  (LinkedIn)\nTop Skills\nOil\nEPC\nFEEDSandeep Sharma\nProject Director EPC at KBR (UK) LIMITED\nCamberley\nSummary\n29+ years of experience of leading and managing teams in\nCorporate and project management roles. Lead by example and\nencourage, inspire, trust and motivate teams through inclusion and\nautonomy in work execution and decision making to successfully\ndeliver on international FEED, EPC projects and growth initiatives. \nKey positions held include Director – Engineering Operations,\nProject Director - EPC, Engineering Manager, Delivery Manager, and\nEngineering & Procurement Integration Manager. \nResponsible for Profit & Loss (P&L) and budget management\non medium to large FEED and EPC projects with all types of\ncommercial models e.g. fixed price, cost plus, reimbursable, Gmax\nand unit rates\nDevelop execution plans and workshare strategies with JV partners\nand High Value execution centers; lead teams of 500+ in multiple\nexecution centers with engineering man-hours budgets of 1.2 MM by\nsuccessfully focusing and aligning the team to objectives with regular\nmonitoring and reporting through KPIs related to budget, schedule,\nresources, HSE targets, milestones and deliverables\nHold regular risks and opportunities workshops with champions\nassigned with mitigation plans implementations. \nRegional level participation on Company vision and strategy\nimplementation of delivery excellence and growth of high\nvalue execution centers in the role of Director - Engineering\nOperations. Operation’s engineering organisation structure & budget\nmanagement and streamlining of systems and processes using lean\nsix sigma principles. Led Strategic growth initiatives for developing\nkey resources for refining and downstream. Performed commercial\nmodels evaluations and Cost estimate development for studies,\nFEED and EPC projects.\nDaily management of Clients relationships, Stakeholder\nmanagement and team building activities \nMajor Projects worked on include Equinor’s Johan Sverdrup Utility\n& Living Quarters EPC, Pacific Northwest LNG Feed,  Shah Deniz\n2, Browse LNG Proposal, Shaybah NGL Program FEED, TOTAL\n  Page 1 of 6\n   \nAntwerp Licensor package, SK HCC Complex FEED, IGD FEED\nfor Habshan 5, Habshan Gas Expansion EPC, OGD III and AGD II\nFEED, Sabine Pass LNG re-gasification EPC, Kuwait PIC Aromatics\nFEED,  Reliance Refinery Offsite and utilities EPC, Gas/Coal based\nPower plants for USA / Mexico EPC\nClients worked with are Equinor, Petronas,  BP, Chevron, TOTAL,\nSaudi Aramco, GASCO, KNPC, SK Energy, Reliance Industries,\nCheniere Energy, Independent Power.Producers in USA/Mexico\nExperience\nKBR (UK)\n7 years 4 months\nProject Director EPC\nAugust 2020 - Present  (7 months)\nLeatherhead, England, United Kingdom\nPrepare and submit proposal for CCS and Energy Transition projects including\nengineering execution strategy, schedule and cost estimates (confidential\nClients)\nDirector - Engineering Operations\nApril 2019 - August 2020  (1 year 5 months)\nLeatherhead, Surrey, United Kingdom\nMember of regional Organisation leadership team for Europe, Asia, Africa and\nAsia Pacific reporting into Senior VP (Regional). Direct reports (30+) include\nengineering department managers, engineering managers, project engineers\nand information/ document manager. \nResponsible for:\n• Development of road map for successful implementation of Company’s vision\non delivery performance and strategic growth of high value execution centers\n• Engineering resource management, chargeability and operations overhead\ncost management\n• Operation Sponsor on projects with regular Client engagement on KPIs, key\nissues and resourcing\n• Near and long-term Clients strategy development\n• New Prospects selections, Bid/ No Bid reviews, Proposals write-ups/\nexecution strategy and estimates reviews \n• Ownership of engineering systems, tools, technical audits and lessons learnt\n• Regional projects performance review of cost, schedule and manhours\n  Page 2 of 6\n   \n• Develop cost estimates, commercial models and execution strategies for new\nproposals\nProject Director - EPC\nApril 2018 - March 2019  (1 year)\nProject Deputy Director and KBR ",
  "emails": [
    "s.sharma4@yahoo.co.uk"
  ],
  "phones": [],
  "names": [
    "Business Manager",
    "Joint Venture",
    "Sverdrup Living"
  ],
  "work_history": [],
  "title": "",
  "company": "",
  "location": "",
  "experience_years": 0,
  "career_stage": "entry",
  "industries": [
    "general"
  ],
  "skills": [
    "leadership",
    "project management"
  ],
  "ai_scores": {
    "experience_years": 0.0,
    "title_progression": 0.5,
    "company_prestige": 0.5,
    "location_mobility": 0.5,
    "skill_diversity": 0.2,
    "network_strength": 0.3
  },
  "ai_final_score": 0.3,
  "ai_processed_at": "2025-08-11T10:42:13.527735",
  "similar_users": [
    {
      "user_id": "file_03a6b852a8c4",
      "similarity_score": 1.0,
      "career_stage": "entry",
      "industries": [
        "general"
      ],
      "ai_score": 0.3,
      "experience_years": 0
    },
    {
      "user_id": "file_051097a5305f",
      "similarity_score": 1.0,
      "career_stage": "entry",
      "industries": [
        "general"
      ],
      "ai_score": 0.3,
      "experience_years": 0
    },
    {
      "user_id": "file_0a18a97bcfd0",
      "similarity_score": 1.0,
      "career_stage": "entry",
      "industries": [
        "general"
      ],
      "ai_score": 0.3,
      "experience_years": 0
    },
    {
      "user_id": "file_0beaec8ab0a1",
      "similarity_score": 1.0,
      "career_stage": "entry",
      "industries": [
        "general"
      ],
      "ai_score": 0.3,
      "experience_years": 0
    },
    {
      "user_id": "file_0cab440865c1",
      "similarity_score": 1.0,
      "career_stage": "entry",
      "industries": [
        "general"
      ],
      "ai_score": 0.3,
      "experience_years": 0
    },
    {
      "user_id": "file_0dfd8954822a",
      "similarity_score": 1.0,
      "career_stage": "entry",
      "industries": [
        "general"
      ],
      "ai_score": 0.3,
      "experience_years": 0
    },
    {
      "user_id": "file_0ff523b92ee7",
      "similarity_score": 1.0,
      "career_stage": "entry",
      "industries": [
        "general"
      ],
      "ai_score": 0.3,
      "experience_years": 0
    },
    {
      "user_id": "file_10d56f91128e",
      "similarity_score": 1.0,
      "career_stage": "entry",
      "industries": [
        "general"
      ],
      "ai_score": 0.3,
      "experience_years": 0
    },
    {
      "user_id": "file_12590c739be9",
      "similarity_score": 1.0,
      "career_stage": "entry",
      "industries": [
        "general"
      ],
      "ai_score": 0.3,
      "experience_years": 0
    },
    {
      "user_id": "file_12df452c4021",
      "similarity_score": 1.0,
      "career_stage": "entry",
      "industries": [
        "general"
      ],
      "ai_score": 0.3,
      "experience_years": 0
    }
  ],
  "recommendations": {
    "career_advancement": [
      "Focus on building core technical skills",
      "Seek mentorship from senior team members",
      "Take on challenging projects to gain experience"
    ],
    "skill_development": [],
    "company_targets": [
      "Mid-size companies with growth potential",
      "Startups in emerging industries",
      "Companies known for employee development"
    ],
    "networking": []
  }
}