{
  "file_id": "file_d3e895d5b889",
  "source_path": "C:\\IntelliCV\\data\\resume_versions\\PARTHA PRATIM BHUYAN - Word Version.docx",
  "extracted_at": "2025-08-10T16:27:03.287502",
  "text": "PARTHA PRATIM BHUYAN\nPROFESSIONAL PROFILE\nAccomplished & versatile professional with over 20 years of experience in the Oil & Gas Industry,\nincluding front line Sales, Technical sales, Engineering design and hands-on experience in operation of refining and petrochemical process units.\nCurrently working as an Account manager responsible for sales of complete UOP portfolio for Kuwait Oman and Bahrain.\nORGANIZATIONAL EXPERIENCE\nJan 2020-Present Account Manager for Kuwait, Oman and Bahrain in UOP.\nDec 2014- Dec 2019 Sales Manager for Catalyst and Adsorbents for KSA, UAE,\nBahrain, Iraq, Jordan in UOP.\nOct 2009- Dec 2014 Technical sales, Hydrocracking catalyst in UOP.\nOct 2005 – Nov 2009 Senior Process Design Engineer in UOP\nAug 2004 - Sep 2005 Process Engineer, Naphtha Cracker, Haldia Petrochem PARTHA PRATIM BHUYAN\nPROFESSIONAL PROFILE\nAccomplished & versatile professional with over 20 years of experience in the Oil & Gas Industry,\nincluding front line Sales, Technical sales, Engineering design and hands-on experience in operation of refining and petrochemical process units.\nCurrently working as an Account manager responsible for sales of complete UOP portfolio for Kuwait Oman and Bahrain.\nORGANIZATIONAL EXPERIENCE\nJan 2020-Present Account Manager for Kuwait, Oman and Bahrain in UOP.\nDec 2014- Dec 2019 Sales Manager for Catalyst and Adsorbents for KSA, UAE,\nBahrain, Iraq, Jordan in UOP.\nOct 2009- Dec 2014 Technical sales, Hydrocracking catalyst in UOP.\nOct 2005 – Nov 2009 Senior Process Design Engineer in UOP\nAug 2004 - Sep 2005 Process Engineer, Naphtha Cracker, Haldia Petrochemicals\nIndia.\nJan 2002 to July 2004 Assistant Engineer, Gas Based Ammonia Plant, Brahmaputra\nValley Fertilizer Corporation Limited India.\nJan 2001 to Dec 2001 Software Engineer, GNRC Infotech , Guwahati, Assam\nWORK EXPERIENCE IN DETAILS\nAccount Manager (Kuwait and Bahrain)\n• Responsible for driving sales and business development for complete UOP portfolio which\nincludes new project sales and aftermarket business.\n• Promote and position UOP gas processing, refining and petrochemical business .\n• Develop and grow UOP’s aftermarket installed base. Aftermarket includes revamps of\nexisting UOP process technology, retrofits and upgrade of UOP equipment, refills of\ncatalyst and adsorbent and sell Honeywell IIOT offering (CPS).\nSales Account Manager (Catalyst and Adsorbent)\n• Responsible for driving the growth of Catalyst and Adsorbent by creating/identifying\nopportunities and ensure momentum in sales cycle for achieving the target. Meet the agreed\nannual sales revenue, direct margin, volumes, price and product mix for catalyst and\nadsorbent portfolio.\n• Ensure to keep opportunity pipeline full with strategic targets and use internal Company\ntools to forecast revenue potential and enhance internal communication to strategize key\naccounts and maximize winning probability.\n• Manage customer relationship to maximise revenue potential in the refining and\npetrochemical sector.\nSales Achievements\n• Expanded UOP’s catalyst foot print in KSA, UAE, Oman, Bahrain, Kuwait by retaining\ncatalyst reload of incumbent units and multiple take away of competitor units for various\ntechnology like CCR Platforming, Hydrocracking, Hydrotreating, Aromatics , Adsorbents\netc.\n• Received PMT President Club Award in 2019 for driving and exceeding revenue target\nof 73M USD by winning multiple Hydrocracking and Hydrotreating and Platforming\ncatalyst reloads.\n• Received PMT President Club Award in 2016 for winning the Bapco Hydrocracker\nreload which was a key take away project and reloading of ADNOC hydrocracker through\npersuasive selling and nose methodology.\n• Received Bravo and Chairman’s team award in 2018 for take away of Saudi Aramco\nRas Tanura Hydrocracker.\n• Received 2014 commercial excellence award for supporting multiple hydrocracking reload\nwins in Europe.\n• Received 2014 HGR team award for winning multiple hydrocracking unit at Tupras for a\ntotal revenue of 20M.\nTechnical Sales Specialist (Hydrocracking)\n• Develop catalyst performance estimates to support sales in reload events of hydrocracking\ncatalysts. Sound knowledge of UOP catalysts & process variables and overall sound\nknowledge of UOP hydrocracking technology.\n• Conduct technical presentations on UOP’s hydrocracking catalyst portfolio and provide\ntechnical proposals of the proposed catalyst system, supporting sales.\n• Liaise with UOP R&D to conduct customer demo pilot plant runs in support of a sales\nreload events. Work up and analyze unit operating-, and pilot plant data to produce\ncatalyst performance estimates.\n• Providing Technical Sales assisting UOP’s salesforce to achieve hydrocracking catalysts\nsales targets.\n• Assist UOP Technical Service in analyzing and troubleshooting catalyst performance\nissues.\n• Develop technical strategies to beat competition in take away catalyst reload projects.\n• Work with customers in providing the right catalyst solution for optimum and best\nperformance of the units. Ac",
  "emails": [],
  "phones": [],
  "names": [
    "Brahmaputra Valley",
    "Haldia Petrochem",
    "Middle East"
  ],
  "work_history": [],
  "title": "",
  "company": "",
  "location": "",
  "experience_years": 0,
  "career_stage": "entry",
  "industries": [
    "general"
  ],
  "skills": [],
  "ai_scores": {
    "experience_years": 0.0,
    "title_progression": 0.5,
    "company_prestige": 0.5,
    "location_mobility": 0.5,
    "skill_diversity": 0.0,
    "network_strength": 0.3
  },
  "ai_final_score": 0.27,
  "ai_processed_at": "2025-08-11T10:42:13.801766",
  "similar_users": [
    {
      "user_id": "file_0003865a7c4a",
      "similarity_score": 1.0,
      "career_stage": "entry",
      "industries": [
        "general"
      ],
      "ai_score": 0.27,
      "experience_years": 0
    },
    {
      "user_id": "file_000a12cbb771",
      "similarity_score": 1.0,
      "career_stage": "entry",
      "industries": [
        "general"
      ],
      "ai_score": 0.27,
      "experience_years": 0
    },
    {
      "user_id": "file_00344b0836c2",
      "similarity_score": 1.0,
      "career_stage": "entry",
      "industries": [
        "general"
      ],
      "ai_score": 0.27,
      "experience_years": 0
    },
    {
      "user_id": "file_0086ec6f1b90",
      "similarity_score": 1.0,
      "career_stage": "entry",
      "industries": [
        "general"
      ],
      "ai_score": 0.27,
      "experience_years": 0
    },
    {
      "user_id": "file_008dcceee73c",
      "similarity_score": 1.0,
      "career_stage": "entry",
      "industries": [
        "general"
      ],
      "ai_score": 0.27,
      "experience_years": 0
    },
    {
      "user_id": "file_00e4daf72a60",
      "similarity_score": 1.0,
      "career_stage": "entry",
      "industries": [
        "general"
      ],
      "ai_score": 0.27,
      "experience_years": 0
    },
    {
      "user_id": "file_00f1ad8aa85c",
      "similarity_score": 1.0,
      "career_stage": "entry",
      "industries": [
        "general"
      ],
      "ai_score": 0.27,
      "experience_years": 0
    },
    {
      "user_id": "file_00f585667d18",
      "similarity_score": 1.0,
      "career_stage": "entry",
      "industries": [
        "general"
      ],
      "ai_score": 0.27,
      "experience_years": 0
    },
    {
      "user_id": "file_010f7e646664",
      "similarity_score": 1.0,
      "career_stage": "entry",
      "industries": [
        "general"
      ],
      "ai_score": 0.27,
      "experience_years": 0
    },
    {
      "user_id": "file_012ae853275f",
      "similarity_score": 1.0,
      "career_stage": "entry",
      "industries": [
        "general"
      ],
      "ai_score": 0.27,
      "experience_years": 0
    }
  ],
  "recommendations": {
    "career_advancement": [
      "Focus on building core technical skills",
      "Seek mentorship from senior team members",
      "Take on challenging projects to gain experience"
    ],
    "skill_development": [],
    "company_targets": [
      "Mid-size companies with growth potential",
      "Startups in emerging industries",
      "Companies known for employee development"
    ],
    "networking": []
  }
}